{
  "updated": "2026-07-03 18:43 UTC",
  "total_attempted": 280,
  "stocks_screened": 275,
  "skipped_count": 5,
  "filters": {
    "size_filter": false,
    "size_min_msek": null,
    "fscore_filter": false,
    "fscore_min": null
  },
  "top50": [
    {
      "name": "Sivers Semiconductors",
      "ticker": "SIVE.ST",
      "price": 49.0,
      "mom_3m": 332.1,
      "mom_6m": 1189.47,
      "mom_12m": 1113.47,
      "compound_score": 2635.04,
      "market_cap_msek": 174637,
      "fscore": 2,
      "rank": 1,
      "prev_rank": 1
    },
    {
      "name": "Medivir",
      "ticker": "MVIR.ST",
      "price": 1.77,
      "mom_3m": -27.46,
      "mom_6m": 402.84,
      "mom_12m": 6.88,
      "compound_score": 382.27,
      "market_cap_msek": 11796,
      "fscore": 2,
      "rank": 2,
      "prev_rank": 4
    },
    {
      "name": "Nokia",
      "ticker": "NOKIA-SEK.ST",
      "price": 119.2,
      "mom_3m": 51.91,
      "mom_6m": 105.71,
      "mom_12m": 142.47,
      "compound_score": 300.09,
      "market_cap_msek": 7212774,
      "fscore": 6,
      "rank": 3,
      "prev_rank": 2
    },
    {
      "name": "Cheffelo",
      "ticker": "CHEF.ST",
      "price": 123.8,
      "mom_3m": 45.54,
      "mom_6m": 68.47,
      "mom_12m": 158.45,
      "compound_score": 272.46,
      "market_cap_msek": 16843,
      "fscore": 6,
      "rank": 4,
      "prev_rank": 5
    },
    {
      "name": "Anoto",
      "ticker": "ANOT.ST",
      "price": 0.12,
      "mom_3m": 17.25,
      "mom_6m": 140.16,
      "mom_12m": 105.5,
      "compound_score": 262.91,
      "market_cap_msek": 1377,
      "fscore": 2,
      "rank": 5,
      "prev_rank": 3
    },
    {
      "name": "Acast",
      "ticker": "ACAST.ST",
      "price": 40.95,
      "mom_3m": 52.8,
      "mom_6m": 27.77,
      "mom_12m": 169.41,
      "compound_score": 249.98,
      "market_cap_msek": 78072,
      "fscore": 5,
      "rank": 6,
      "prev_rank": 7
    },
    {
      "name": "Episurf Medical",
      "ticker": "EPIS-B.ST",
      "price": 0.08,
      "mom_3m": 36.29,
      "mom_6m": 182.61,
      "mom_12m": -14.56,
      "compound_score": 204.34,
      "market_cap_msek": 5240,
      "fscore": 2,
      "rank": 7,
      "prev_rank": 6
    },
    {
      "name": "NCAB Group",
      "ticker": "NCAB.ST",
      "price": 78.7,
      "mom_3m": 48.94,
      "mom_6m": 67.3,
      "mom_12m": 82.93,
      "compound_score": 199.17,
      "market_cap_msek": 160982,
      "fscore": 7,
      "rank": 8,
      "prev_rank": 8
    },
    {
      "name": "Inission",
      "ticker": "INISS-B.ST",
      "price": 74.6,
      "mom_3m": 32.02,
      "mom_6m": 53.89,
      "mom_12m": 100.67,
      "compound_score": 186.57,
      "market_cap_msek": 17949,
      "fscore": 6,
      "rank": 9,
      "prev_rank": 10
    },
    {
      "name": "Midsona B",
      "ticker": "MSON-B.ST",
      "price": 15.1,
      "mom_3m": 27.0,
      "mom_6m": 81.22,
      "mom_12m": 78.27,
      "compound_score": 186.49,
      "market_cap_msek": 22676,
      "fscore": 6,
      "rank": 10,
      "prev_rank": 16
    },
    {
      "name": "Boozt",
      "ticker": "BOOZT.ST",
      "price": 147.0,
      "mom_3m": 68.48,
      "mom_6m": 33.27,
      "mom_12m": 83.41,
      "compound_score": 185.16,
      "market_cap_msek": 92628,
      "fscore": 7,
      "rank": 11,
      "prev_rank": 14
    },
    {
      "name": "Lundin Mining",
      "ticker": "LUMI.ST",
      "price": 234.8,
      "mom_3m": 9.32,
      "mom_6m": 24.26,
      "mom_12m": 143.09,
      "compound_score": 176.67,
      "market_cap_msek": 2140649,
      "fscore": 6,
      "rank": 12,
      "prev_rank": 11
    },
    {
      "name": "Humana",
      "ticker": "HUM.ST",
      "price": 66.7,
      "mom_3m": 49.1,
      "mom_6m": 41.11,
      "mom_12m": 84.91,
      "compound_score": 175.12,
      "market_cap_msek": 33032,
      "fscore": 5,
      "rank": 13,
      "prev_rank": null
    },
    {
      "name": "Cint Group",
      "ticker": "CINT.ST",
      "price": 5.97,
      "mom_3m": 58.86,
      "mom_6m": 127.86,
      "mom_12m": -15.02,
      "compound_score": 171.71,
      "market_cap_msek": 22260,
      "fscore": 5,
      "rank": 14,
      "prev_rank": 21
    },
    {
      "name": "ABB",
      "ticker": "ABB.ST",
      "price": 1021.0,
      "mom_3m": 32.46,
      "mom_6m": 52.53,
      "mom_12m": 83.53,
      "compound_score": 168.52,
      "market_cap_msek": 19989755,
      "fscore": 7,
      "rank": 15,
      "prev_rank": 12
    },
    {
      "name": "Sinch",
      "ticker": "SINCH.ST",
      "price": 40.42,
      "mom_3m": 74.45,
      "mom_6m": 30.89,
      "mom_12m": 57.4,
      "compound_score": 162.74,
      "market_cap_msek": 293546,
      "fscore": 5,
      "rank": 16,
      "prev_rank": 25
    },
    {
      "name": "Attendo",
      "ticker": "ATT.ST",
      "price": 116.7,
      "mom_3m": 16.78,
      "mom_6m": 46.96,
      "mom_12m": 92.66,
      "compound_score": 156.41,
      "market_cap_msek": 175616,
      "fscore": 5,
      "rank": 17,
      "prev_rank": 13
    },
    {
      "name": "Mycronic",
      "ticker": "MYCR.ST",
      "price": 303.2,
      "mom_3m": 40.55,
      "mom_6m": 43.24,
      "mom_12m": 67.6,
      "compound_score": 151.39,
      "market_cap_msek": 626173,
      "fscore": 6,
      "rank": 18,
      "prev_rank": 17
    },
    {
      "name": "Sandvik",
      "ticker": "SAND.ST",
      "price": 394.6,
      "mom_3m": 15.39,
      "mom_6m": 41.0,
      "mom_12m": 88.2,
      "compound_score": 144.59,
      "market_cap_msek": 5423839,
      "fscore": 7,
      "rank": 19,
      "prev_rank": 19
    },
    {
      "name": "Swedish Orphan Biovitrum",
      "ticker": "SOBI.ST",
      "price": 479.6,
      "mom_3m": 25.22,
      "mom_6m": 47.03,
      "mom_12m": 70.92,
      "compound_score": 143.17,
      "market_cap_msek": 1746534,
      "fscore": 5,
      "rank": 20,
      "prev_rank": 24
    },
    {
      "name": "Catena Media",
      "ticker": "CTM.ST",
      "price": 2.72,
      "mom_3m": 26.22,
      "mom_6m": 60.19,
      "mom_12m": 51.28,
      "compound_score": 137.69,
      "market_cap_msek": 2371,
      "fscore": 5,
      "rank": 21,
      "prev_rank": 28
    },
    {
      "name": "Mildef Group",
      "ticker": "MILDEF.ST",
      "price": 195.0,
      "mom_3m": 69.08,
      "mom_6m": 62.48,
      "mom_12m": 3.92,
      "compound_score": 135.48,
      "market_cap_msek": 96130,
      "fscore": 7,
      "rank": 22,
      "prev_rank": null
    },
    {
      "name": "Hexatronic",
      "ticker": "HTRO.ST",
      "price": 37.8,
      "mom_3m": 11.37,
      "mom_6m": 71.74,
      "mom_12m": 49.17,
      "compound_score": 132.28,
      "market_cap_msek": 87768,
      "fscore": 5,
      "rank": 23,
      "prev_rank": 15
    },
    {
      "name": "Instalco",
      "ticker": "INSTAL.ST",
      "price": 37.0,
      "mom_3m": 18.68,
      "mom_6m": 54.23,
      "mom_12m": 56.68,
      "compound_score": 129.59,
      "market_cap_msek": 107335,
      "fscore": 6,
      "rank": 24,
      "prev_rank": 9
    },
    {
      "name": "Vicore Pharma",
      "ticker": "VICO.ST",
      "price": 13.0,
      "mom_3m": 28.46,
      "mom_6m": 32.38,
      "mom_12m": 62.91,
      "compound_score": 123.75,
      "market_cap_msek": 39729,
      "fscore": 3,
      "rank": 25,
      "prev_rank": null
    },
    {
      "name": "Bravida",
      "ticker": "BRAV.ST",
      "price": 124.2,
      "mom_3m": 31.93,
      "mom_6m": 48.27,
      "mom_12m": 43.18,
      "compound_score": 123.38,
      "market_cap_msek": 273124,
      "fscore": 6,
      "rank": 26,
      "prev_rank": 18
    },
    {
      "name": "Viaplay B",
      "ticker": "VPLAY-B.ST",
      "price": 1.27,
      "mom_3m": -10.28,
      "mom_6m": 39.66,
      "mom_12m": 91.87,
      "compound_score": 121.25,
      "market_cap_msek": 60734,
      "fscore": 3,
      "rank": 27,
      "prev_rank": 33
    },
    {
      "name": "Ependion",
      "ticker": "EPEN.ST",
      "price": 140.8,
      "mom_3m": 52.23,
      "mom_6m": 31.55,
      "mom_12m": 37.39,
      "compound_score": 121.18,
      "market_cap_msek": 47254,
      "fscore": 6,
      "rank": 28,
      "prev_rank": 26
    },
    {
      "name": "SSAB B",
      "ticker": "SSAB-B.ST",
      "price": 89.52,
      "mom_3m": 25.12,
      "mom_6m": 32.29,
      "mom_12m": 63.09,
      "compound_score": 120.49,
      "market_cap_msek": 977785,
      "fscore": 7,
      "rank": 29,
      "prev_rank": 20
    },
    {
      "name": "Infant Bacterial",
      "ticker": "IBT-B.ST",
      "price": 69.9,
      "mom_3m": 43.53,
      "mom_6m": 43.24,
      "mom_12m": 31.89,
      "compound_score": 118.66,
      "market_cap_msek": 9901,
      "fscore": 3,
      "rank": 30,
      "prev_rank": 50
    },
    {
      "name": "Clavister Holding",
      "ticker": "CLAV.ST",
      "price": 5.14,
      "mom_3m": 22.97,
      "mom_6m": 84.89,
      "mom_12m": 7.19,
      "compound_score": 115.05,
      "market_cap_msek": 20943,
      "fscore": 5,
      "rank": 31,
      "prev_rank": null
    },
    {
      "name": "Eltel",
      "ticker": "ELTEL.ST",
      "price": 12.2,
      "mom_3m": 46.28,
      "mom_6m": 32.32,
      "mom_12m": 34.36,
      "compound_score": 112.97,
      "market_cap_msek": 22382,
      "fscore": 3,
      "rank": 32,
      "prev_rank": 22
    },
    {
      "name": "Clas Ohlson",
      "ticker": "CLAS-B.ST",
      "price": 437.8,
      "mom_3m": 22.09,
      "mom_6m": 51.98,
      "mom_12m": 37.41,
      "compound_score": 111.48,
      "market_cap_msek": 293399,
      "fscore": 6,
      "rank": 33,
      "prev_rank": 30
    },
    {
      "name": "Boliden",
      "ticker": "BOL.ST",
      "price": 525.2,
      "mom_3m": 14.22,
      "mom_6m": 9.18,
      "mom_12m": 86.93,
      "compound_score": 110.33,
      "market_cap_msek": 1573056,
      "fscore": 7,
      "rank": 34,
      "prev_rank": 37
    },
    {
      "name": "Scandi Standard",
      "ticker": "SCST.ST",
      "price": 147.6,
      "mom_3m": 3.32,
      "mom_6m": 52.08,
      "mom_12m": 54.18,
      "compound_score": 109.57,
      "market_cap_msek": 102108,
      "fscore": 6,
      "rank": 35,
      "prev_rank": 29
    },
    {
      "name": "Eniro",
      "ticker": "ENRO.ST",
      "price": 27.1,
      "mom_3m": 8.47,
      "mom_6m": 55.13,
      "mom_12m": 43.4,
      "compound_score": 107.0,
      "market_cap_msek": 4258,
      "fscore": 4,
      "rank": 36,
      "prev_rank": 40
    },
    {
      "name": "Ferronordic",
      "ticker": "FNM.ST",
      "price": 60.6,
      "mom_3m": 37.1,
      "mom_6m": 38.99,
      "mom_12m": 29.49,
      "compound_score": 105.58,
      "market_cap_msek": 9003,
      "fscore": 4,
      "rank": 37,
      "prev_rank": 23
    },
    {
      "name": "Cloetta",
      "ticker": "CLA-B.ST",
      "price": 52.05,
      "mom_3m": 4.88,
      "mom_6m": 34.73,
      "mom_12m": 60.89,
      "compound_score": 100.5,
      "market_cap_msek": 157281,
      "fscore": 6,
      "rank": 38,
      "prev_rank": 39
    },
    {
      "name": "Bufab",
      "ticker": "BUFAB.ST",
      "price": 129.6,
      "mom_3m": 23.16,
      "mom_6m": 28.33,
      "mom_12m": 48.77,
      "compound_score": 100.26,
      "market_cap_msek": 256115,
      "fscore": 6,
      "rank": 39,
      "prev_rank": 35
    },
    {
      "name": "Orrön Energy",
      "ticker": "ORRON.ST",
      "price": 7.47,
      "mom_3m": 10.18,
      "mom_6m": 45.33,
      "mom_12m": 44.21,
      "compound_score": 99.72,
      "market_cap_msek": 22485,
      "fscore": 4,
      "rank": 40,
      "prev_rank": 48
    },
    {
      "name": "Railcare",
      "ticker": "RAIL.ST",
      "price": 35.8,
      "mom_3m": 32.87,
      "mom_6m": 24.71,
      "mom_12m": 41.35,
      "compound_score": 98.93,
      "market_cap_msek": 9119,
      "fscore": 5,
      "rank": 41,
      "prev_rank": 32
    },
    {
      "name": "Karnell Group",
      "ticker": "KARNEL-B.ST",
      "price": 80.9,
      "mom_3m": 34.83,
      "mom_6m": 16.07,
      "mom_12m": 47.09,
      "compound_score": 97.99,
      "market_cap_msek": 45893,
      "fscore": 6,
      "rank": 42,
      "prev_rank": 34
    },
    {
      "name": "Asmodee",
      "ticker": "ASMDEE-B.ST",
      "price": 144.7,
      "mom_3m": 41.39,
      "mom_6m": 39.38,
      "mom_12m": 15.8,
      "compound_score": 96.56,
      "market_cap_msek": 367368,
      "fscore": 6,
      "rank": 43,
      "prev_rank": null
    },
    {
      "name": "Loomis",
      "ticker": "LOOMIS.ST",
      "price": 492.2,
      "mom_3m": 21.52,
      "mom_6m": 36.67,
      "mom_12m": 36.59,
      "compound_score": 94.78,
      "market_cap_msek": 346845,
      "fscore": 7,
      "rank": 44,
      "prev_rank": 41
    },
    {
      "name": "Nilörngruppen",
      "ticker": "NIL-B.ST",
      "price": 74.7,
      "mom_3m": 53.04,
      "mom_6m": 20.21,
      "mom_12m": 20.97,
      "compound_score": 94.23,
      "market_cap_msek": 8919,
      "fscore": 6,
      "rank": 45,
      "prev_rank": 38
    },
    {
      "name": "Alfa Laval",
      "ticker": "ALFA.ST",
      "price": 578.8,
      "mom_3m": 14.04,
      "mom_6m": 31.12,
      "mom_12m": 47.01,
      "compound_score": 92.17,
      "market_cap_msek": 2555349,
      "fscore": 6,
      "rank": 46,
      "prev_rank": null
    },
    {
      "name": "Hanza",
      "ticker": "HANZA.ST",
      "price": 138.4,
      "mom_3m": -5.02,
      "mom_6m": 18.93,
      "mom_12m": 76.51,
      "compound_score": 90.43,
      "market_cap_msek": 93764,
      "fscore": 6,
      "rank": 47,
      "prev_rank": 31
    },
    {
      "name": "Gränges",
      "ticker": "GRNG.ST",
      "price": 169.1,
      "mom_3m": 18.72,
      "mom_6m": 25.72,
      "mom_12m": 45.47,
      "compound_score": 89.91,
      "market_cap_msek": 193665,
      "fscore": 6,
      "rank": 48,
      "prev_rank": 42
    },
    {
      "name": "Hansa Biopharma",
      "ticker": "HNSA.ST",
      "price": 35.0,
      "mom_3m": 14.38,
      "mom_6m": 25.27,
      "mom_12m": 47.43,
      "compound_score": 87.08,
      "market_cap_msek": 36527,
      "fscore": 3,
      "rank": 49,
      "prev_rank": null
    },
    {
      "name": "Ambea",
      "ticker": "AMBEA.ST",
      "price": 159.0,
      "mom_3m": 22.2,
      "mom_6m": 16.57,
      "mom_12m": 46.27,
      "compound_score": 85.04,
      "market_cap_msek": 132176,
      "fscore": 6,
      "rank": 50,
      "prev_rank": null
    }
  ],
  "skipped": [
    {
      "name": "Maha Capital",
      "ticker": "MAHA-A.ST",
      "reason": "Insufficient history (need 265d, have 21d)",
      "days_available": 21
    },
    {
      "name": "Hacksaw",
      "ticker": "HACK.ST",
      "reason": "Insufficient history (need 265d, have 256d)",
      "days_available": 256
    },
    {
      "name": "Formpipe Software",
      "ticker": "FPIP.ST",
      "reason": "Insufficient history (need 265d, have 22d)",
      "days_available": 22
    },
    {
      "name": "CoinShares",
      "ticker": "CS.ST",
      "reason": "No price data",
      "days_available": 0
    },
    {
      "name": "Verisure",
      "ticker": "VSURE.ST",
      "reason": "No price data",
      "days_available": 0
    }
  ]
}